twirp/__init__.py
twirp/asgi.py
twirp/base.py
twirp/client.py
twirp/context.py
twirp/ctxkeys.py
twirp/errors.py
twirp/exceptions.py
twirp/hook.py
twirp/logging.py
twirp/server.py
twirp-0.0.7.dist-info/LICENSE
twirp-0.0.7.dist-info/METADATA
twirp-0.0.7.dist-info/WHEEL
twirp-0.0.7.dist-info/top_level.txt
twirp-0.0.7.dist-info/RECORD
