Metadata-Version: 2.1
Name: twirp
Version: 0.0.7
Summary: Twirp server and client lib
Home-page: UNKNOWN
License: UNKNOWN
Platform: UNKNOWN
License-File: LICENSE
